emoFeatExtract/__init__.py
emoFeatExtract/emoFeatExtract.py
tests/__init__.py
tests/test.py
tests/test2.py
tests/test3.py
tests/testEmoDB.py
tests/testRAVDESS.py
emoFeatExtract-0.0.1.dist-info/LICENSE
emoFeatExtract-0.0.1.dist-info/METADATA
emoFeatExtract-0.0.1.dist-info/WHEEL
emoFeatExtract-0.0.1.dist-info/top_level.txt
emoFeatExtract-0.0.1.dist-info/RECORD
