Metadata-Version: 2.1
Name: emoFeatExtract
Version: 0.0.1
Summary: A speech emotional recognition package
Home-page: https://github.com/KonstantinosAnd/emoFeatExtract
Author: Konstantinos Andriopoulos
Author-email: konstantinosand@gmail.com
License: UNKNOWN
Platform: UNKNOWN
Classifier: Programming Language :: Python :: 3
Classifier: License :: OSI Approved :: MIT License
Classifier: Operating System :: OS Independent
Requires-Python: >=3.6
